{"traces":{"/home/usuario/Escritorio/reporte/club/lib.rs":[{"line":5,"address":[808561,808364],"length":1,"stats":{"Line":0},"fn_name":null},{"line":118,"address":[860128,860768],"length":1,"stats":{"Line":0},"fn_name":"new"},{"line":119,"address":[860145],"length":1,"stats":{"Line":0},"fn_name":null},{"line":120,"address":[860183],"length":1,"stats":{"Line":0},"fn_name":null},{"line":121,"address":[860240],"length":1,"stats":{"Line":0},"fn_name":null},{"line":122,"address":[860297],"length":1,"stats":{"Line":0},"fn_name":null},{"line":123,"address":[860322],"length":1,"stats":{"Line":0},"fn_name":null},{"line":124,"address":[860350],"length":1,"stats":{"Line":0},"fn_name":null},{"line":125,"address":[860378],"length":1,"stats":{"Line":0},"fn_name":null},{"line":126,"address":[860399],"length":1,"stats":{"Line":0},"fn_name":null},{"line":127,"address":[860404],"length":1,"stats":{"Line":0},"fn_name":null},{"line":128,"address":[860412],"length":1,"stats":{"Line":0},"fn_name":null},{"line":129,"address":[860436],"length":1,"stats":{"Line":0},"fn_name":null},{"line":140,"address":[860695],"length":1,"stats":{"Line":0},"fn_name":null},{"line":146,"address":[870208],"length":1,"stats":{"Line":0},"fn_name":"guardar_firma"},{"line":147,"address":[870221],"length":1,"stats":{"Line":0},"fn_name":null},{"line":156,"address":[870320],"length":1,"stats":{"Line":0},"fn_name":"es_owner"},{"line":157,"address":[870333],"length":1,"stats":{"Line":0},"fn_name":null},{"line":158,"address":[870338],"length":1,"stats":{"Line":0},"fn_name":null},{"line":159,"address":[870359],"length":1,"stats":{"Line":0},"fn_name":null},{"line":160,"address":[870416,870454],"length":1,"stats":{"Line":0},"fn_name":null},{"line":161,"address":[870449],"length":1,"stats":{"Line":0},"fn_name":null},{"line":174,"address":[860876],"length":1,"stats":{"Line":0},"fn_name":null},{"line":175,"address":[860867,860950],"length":1,"stats":{"Line":0},"fn_name":null},{"line":176,"address":[860891],"length":1,"stats":{"Line":0},"fn_name":null},{"line":186,"address":[860983],"length":1,"stats":{"Line":0},"fn_name":null},{"line":187,"address":[861011,860974],"length":1,"stats":{"Line":0},"fn_name":null},{"line":188,"address":[860993],"length":1,"stats":{"Line":0},"fn_name":null},{"line":199,"address":[870464],"length":1,"stats":{"Line":0},"fn_name":"aceptar_modificaciones"},{"line":200,"address":[870477],"length":1,"stats":{"Line":0},"fn_name":null},{"line":201,"address":[870520,870482],"length":1,"stats":{"Line":0},"fn_name":null},{"line":202,"address":[870509],"length":1,"stats":{"Line":0},"fn_name":null},{"line":214,"address":[870528],"length":1,"stats":{"Line":0},"fn_name":"esta_permitido"},{"line":215,"address":[870541],"length":1,"stats":{"Line":0},"fn_name":null},{"line":216,"address":[870546],"length":1,"stats":{"Line":0},"fn_name":null},{"line":217,"address":[870567,870613],"length":1,"stats":{"Line":0},"fn_name":null},{"line":218,"address":[870615],"length":1,"stats":{"Line":0},"fn_name":null},{"line":220,"address":[870602],"length":1,"stats":{"Line":0},"fn_name":null},{"line":235,"address":[861305,861024],"length":1,"stats":{"Line":0},"fn_name":"agregar_direccion"},{"line":236,"address":[861049],"length":1,"stats":{"Line":0},"fn_name":null},{"line":237,"address":[861054],"length":1,"stats":{"Line":0},"fn_name":null},{"line":238,"address":[861130],"length":1,"stats":{"Line":0},"fn_name":null},{"line":239,"address":[861235],"length":1,"stats":{"Line":0},"fn_name":null},{"line":240,"address":[861300],"length":1,"stats":{"Line":0},"fn_name":null},{"line":242,"address":[861163],"length":1,"stats":{"Line":0},"fn_name":null},{"line":245,"address":[861063],"length":1,"stats":{"Line":0},"fn_name":null},{"line":260,"address":[861328,861621],"length":1,"stats":{"Line":0},"fn_name":"eliminar_direccion"},{"line":261,"address":[861353],"length":1,"stats":{"Line":0},"fn_name":null},{"line":262,"address":[861358],"length":1,"stats":{"Line":0},"fn_name":null},{"line":263,"address":[861437],"length":1,"stats":{"Line":0},"fn_name":null},{"line":264,"address":[861446],"length":1,"stats":{"Line":0},"fn_name":null},{"line":265,"address":[861667,861544],"length":1,"stats":{"Line":0},"fn_name":null},{"line":266,"address":[861636,861672],"length":1,"stats":{"Line":0},"fn_name":null},{"line":268,"address":[861589],"length":1,"stats":{"Line":0},"fn_name":null},{"line":269,"address":[861616],"length":1,"stats":{"Line":0},"fn_name":null},{"line":270,"address":[861477],"length":1,"stats":{"Line":0},"fn_name":null},{"line":272,"address":[861367],"length":1,"stats":{"Line":0},"fn_name":null},{"line":288,"address":[879985,863064,861712],"length":1,"stats":{"Line":0},"fn_name":"registrar_socio"},{"line":289,"address":[861783],"length":1,"stats":{"Line":0},"fn_name":null},{"line":290,"address":[861901,861839],"length":1,"stats":{"Line":0},"fn_name":null},{"line":291,"address":[861973],"length":1,"stats":{"Line":0},"fn_name":null},{"line":292,"address":[862050],"length":1,"stats":{"Line":0},"fn_name":null},{"line":293,"address":[862099,862165],"length":1,"stats":{"Line":0},"fn_name":null},{"line":294,"address":[862249,862142,862210],"length":1,"stats":{"Line":0},"fn_name":null},{"line":295,"address":[862311,862263,862226],"length":1,"stats":{"Line":0},"fn_name":null},{"line":296,"address":[862269,863134],"length":1,"stats":{"Line":0},"fn_name":null},{"line":298,"address":[862189,862342],"length":1,"stats":{"Line":0},"fn_name":null},{"line":299,"address":[862358],"length":1,"stats":{"Line":0},"fn_name":null},{"line":300,"address":[862432],"length":1,"stats":{"Line":0},"fn_name":null},{"line":301,"address":[862475],"length":1,"stats":{"Line":0},"fn_name":null},{"line":302,"address":[862494],"length":1,"stats":{"Line":0},"fn_name":null},{"line":303,"address":[862572],"length":1,"stats":{"Line":0},"fn_name":null},{"line":304,"address":[862674],"length":1,"stats":{"Line":0},"fn_name":null},{"line":305,"address":[862698],"length":1,"stats":{"Line":0},"fn_name":null},{"line":306,"address":[862921],"length":1,"stats":{"Line":0},"fn_name":null},{"line":307,"address":[863040],"length":1,"stats":{"Line":0},"fn_name":null},{"line":308,"address":[863112,863162,862521,863048,862000,862599,863079],"length":1,"stats":{"Line":0},"fn_name":null},{"line":309,"address":[861907,863188],"length":1,"stats":{"Line":0},"fn_name":null},{"line":320,"address":[870640],"length":1,"stats":{"Line":0},"fn_name":"calcular_precio"},{"line":321,"address":[870667],"length":1,"stats":{"Line":0},"fn_name":null},{"line":322,"address":[870709],"length":1,"stats":{"Line":0},"fn_name":null},{"line":323,"address":[870745],"length":1,"stats":{"Line":0},"fn_name":null},{"line":324,"address":[870781],"length":1,"stats":{"Line":0},"fn_name":null},{"line":326,"address":[870805],"length":1,"stats":{"Line":0},"fn_name":null},{"line":329,"address":[870844],"length":1,"stats":{"Line":0},"fn_name":null},{"line":339,"address":[870912],"length":1,"stats":{"Line":0},"fn_name":"crear_pago_pendiente"},{"line":340,"address":[870998,871124],"length":1,"stats":{"Line":0},"fn_name":null},{"line":342,"address":[871072],"length":1,"stats":{"Line":0},"fn_name":null},{"line":343,"address":[871084],"length":1,"stats":{"Line":0},"fn_name":null},{"line":344,"address":[871092],"length":1,"stats":{"Line":0},"fn_name":null},{"line":345,"address":[871396,871100,871189],"length":1,"stats":{"Line":0},"fn_name":null},{"line":346,"address":[871197],"length":1,"stats":{"Line":0},"fn_name":null},{"line":347,"address":[871263],"length":1,"stats":{"Line":0},"fn_name":null},{"line":348,"address":[871374],"length":1,"stats":{"Line":0},"fn_name":null},{"line":361,"address":[871440],"length":1,"stats":{"Line":0},"fn_name":"buscar_socio"},{"line":362,"address":[871474],"length":1,"stats":{"Line":0},"fn_name":null},{"line":363,"address":[871479],"length":1,"stats":{"Line":0},"fn_name":null},{"line":364,"address":[871493],"length":1,"stats":{"Line":0},"fn_name":null},{"line":365,"address":[871658,871573,871672],"length":1,"stats":{"Line":0},"fn_name":null},{"line":366,"address":[871653],"length":1,"stats":{"Line":0},"fn_name":null},{"line":368,"address":[871667,871677,871631],"length":1,"stats":{"Line":0},"fn_name":null},{"line":371,"address":[871552],"length":1,"stats":{"Line":0},"fn_name":null},{"line":372,"address":[871718],"length":1,"stats":{"Line":0},"fn_name":null},{"line":374,"address":[871707],"length":1,"stats":{"Line":0},"fn_name":null},{"line":391,"address":[871760],"length":1,"stats":{"Line":0},"fn_name":"primero_pagos_pendientes"},{"line":392,"address":[871774],"length":1,"stats":{"Line":0},"fn_name":null},{"line":405,"address":[863793],"length":1,"stats":{"Line":0},"fn_name":null},{"line":406,"address":[863352],"length":1,"stats":{"Line":0},"fn_name":null},{"line":408,"address":[863441],"length":1,"stats":{"Line":0},"fn_name":null},{"line":409,"address":[863459],"length":1,"stats":{"Line":0},"fn_name":null},{"line":411,"address":[863493],"length":1,"stats":{"Line":0},"fn_name":null},{"line":413,"address":[863675],"length":1,"stats":{"Line":0},"fn_name":null},{"line":414,"address":[863704],"length":1,"stats":{"Line":0},"fn_name":null},{"line":416,"address":[863757,863888,863811],"length":1,"stats":{"Line":0},"fn_name":null},{"line":417,"address":[863860],"length":1,"stats":{"Line":0},"fn_name":null},{"line":419,"address":[863928],"length":1,"stats":{"Line":0},"fn_name":null},{"line":421,"address":[864055],"length":1,"stats":{"Line":0},"fn_name":null},{"line":423,"address":[864106],"length":1,"stats":{"Line":0},"fn_name":null},{"line":424,"address":[864132],"length":1,"stats":{"Line":0},"fn_name":null},{"line":425,"address":[864174],"length":1,"stats":{"Line":0},"fn_name":null},{"line":427,"address":[864225],"length":1,"stats":{"Line":0},"fn_name":null},{"line":430,"address":[863982],"length":1,"stats":{"Line":0},"fn_name":null},{"line":435,"address":[863600],"length":1,"stats":{"Line":0},"fn_name":null},{"line":438,"address":[863535],"length":1,"stats":{"Line":0},"fn_name":null},{"line":442,"address":[863361],"length":1,"stats":{"Line":0},"fn_name":null},{"line":456,"address":[864288,864852],"length":1,"stats":{"Line":0},"fn_name":"consultar_pagos"},{"line":457,"address":[864341],"length":1,"stats":{"Line":0},"fn_name":null},{"line":459,"address":[864415],"length":1,"stats":{"Line":0},"fn_name":null},{"line":460,"address":[864424],"length":1,"stats":{"Line":0},"fn_name":null},{"line":461,"address":[864429,865067],"length":1,"stats":{"Line":0},"fn_name":null},{"line":462,"address":[864469],"length":1,"stats":{"Line":0},"fn_name":null},{"line":463,"address":[864549],"length":1,"stats":{"Line":0},"fn_name":null},{"line":464,"address":[864583,864865],"length":1,"stats":{"Line":0},"fn_name":null},{"line":465,"address":[864881],"length":1,"stats":{"Line":0},"fn_name":null},{"line":466,"address":[809629,809616,809680,809693],"length":1,"stats":{"Line":0},"fn_name":"{closure#0}"},{"line":468,"address":[865072],"length":1,"stats":{"Line":0},"fn_name":null},{"line":470,"address":[809725,809712],"length":1,"stats":{"Line":0},"fn_name":"{closure#2}"},{"line":477,"address":[864350],"length":1,"stats":{"Line":0},"fn_name":null},{"line":485,"address":[871856],"length":1,"stats":{"Line":0},"fn_name":"descuento_otorgado"},{"line":486,"address":[871904],"length":1,"stats":{"Line":0},"fn_name":null},{"line":487,"address":[871931],"length":1,"stats":{"Line":0},"fn_name":null},{"line":488,"address":[871971],"length":1,"stats":{"Line":0},"fn_name":null},{"line":489,"address":[871991,872010],"length":1,"stats":{"Line":0},"fn_name":null},{"line":490,"address":[872036],"length":1,"stats":{"Line":0},"fn_name":null},{"line":493,"address":[871999],"length":1,"stats":{"Line":0},"fn_name":null},{"line":504,"address":[865179],"length":1,"stats":{"Line":0},"fn_name":null},{"line":505,"address":[865206,865170],"length":1,"stats":{"Line":0},"fn_name":null},{"line":506,"address":[865199],"length":1,"stats":{"Line":0},"fn_name":null},{"line":518,"address":[865259],"length":1,"stats":{"Line":0},"fn_name":null},{"line":519,"address":[865287,865250],"length":1,"stats":{"Line":0},"fn_name":null},{"line":520,"address":[865279],"length":1,"stats":{"Line":0},"fn_name":null},{"line":537,"address":[865296,867528],"length":1,"stats":{"Line":0},"fn_name":"crear_pagos"},{"line":538,"address":[865337],"length":1,"stats":{"Line":0},"fn_name":null},{"line":539,"address":[865367],"length":1,"stats":{"Line":0},"fn_name":null},{"line":540,"address":[809808,809744,809824,809757],"length":1,"stats":{"Line":0},"fn_name":"{closure#0}"},{"line":541,"address":[809840,809859],"length":1,"stats":{"Line":0},"fn_name":"{closure#2}"},{"line":542,"address":[865901],"length":1,"stats":{"Line":0},"fn_name":null},{"line":544,"address":[865909],"length":1,"stats":{"Line":0},"fn_name":null},{"line":545,"address":[865980],"length":1,"stats":{"Line":0},"fn_name":null},{"line":546,"address":[809997,809920,809933,809984],"length":1,"stats":{"Line":0},"fn_name":"{closure#3}"},{"line":547,"address":[866320],"length":1,"stats":{"Line":0},"fn_name":null},{"line":548,"address":[866375],"length":1,"stats":{"Line":0},"fn_name":null},{"line":549,"address":[866508],"length":1,"stats":{"Line":0},"fn_name":null},{"line":550,"address":[866567],"length":1,"stats":{"Line":0},"fn_name":null},{"line":552,"address":[866694],"length":1,"stats":{"Line":0},"fn_name":null},{"line":553,"address":[866783],"length":1,"stats":{"Line":0},"fn_name":null},{"line":554,"address":[866830],"length":1,"stats":{"Line":0},"fn_name":null},{"line":555,"address":[866907,866978],"length":1,"stats":{"Line":0},"fn_name":null},{"line":556,"address":[866954],"length":1,"stats":{"Line":0},"fn_name":null},{"line":557,"address":[866970],"length":1,"stats":{"Line":0},"fn_name":null},{"line":561,"address":[866991,866660,867088],"length":1,"stats":{"Line":0},"fn_name":null},{"line":563,"address":[867052],"length":1,"stats":{"Line":0},"fn_name":null},{"line":564,"address":[867064,867136,867243],"length":1,"stats":{"Line":0},"fn_name":null},{"line":566,"address":[867144],"length":1,"stats":{"Line":0},"fn_name":null},{"line":568,"address":[867284],"length":1,"stats":{"Line":0},"fn_name":null},{"line":569,"address":[867403],"length":1,"stats":{"Line":0},"fn_name":null},{"line":573,"address":[866585],"length":1,"stats":{"Line":0},"fn_name":null},{"line":578,"address":[865392],"length":1,"stats":{"Line":0},"fn_name":null},{"line":580,"address":[866068],"length":1,"stats":{"Line":0},"fn_name":null},{"line":582,"address":[865346],"length":1,"stats":{"Line":0},"fn_name":null},{"line":591,"address":[867585],"length":1,"stats":{"Line":0},"fn_name":null},{"line":592,"address":[867576],"length":1,"stats":{"Line":0},"fn_name":null},{"line":593,"address":[867595],"length":1,"stats":{"Line":0},"fn_name":null},{"line":603,"address":[867649],"length":1,"stats":{"Line":0},"fn_name":null},{"line":604,"address":[867640],"length":1,"stats":{"Line":0},"fn_name":null},{"line":605,"address":[867659],"length":1,"stats":{"Line":0},"fn_name":null},{"line":615,"address":[867713],"length":1,"stats":{"Line":0},"fn_name":null},{"line":616,"address":[867704],"length":1,"stats":{"Line":0},"fn_name":null},{"line":617,"address":[867723],"length":1,"stats":{"Line":0},"fn_name":null},{"line":628,"address":[867744,867775],"length":1,"stats":{"Line":0},"fn_name":"get_categoria_a"},{"line":629,"address":[867757],"length":1,"stats":{"Line":0},"fn_name":null},{"line":630,"address":[867766,867825],"length":1,"stats":{"Line":0},"fn_name":null},{"line":631,"address":[867799],"length":1,"stats":{"Line":0},"fn_name":null},{"line":642,"address":[867871,867840],"length":1,"stats":{"Line":0},"fn_name":"get_categoria_b"},{"line":643,"address":[867853],"length":1,"stats":{"Line":0},"fn_name":null},{"line":644,"address":[867862,867924],"length":1,"stats":{"Line":0},"fn_name":null},{"line":645,"address":[867895],"length":1,"stats":{"Line":0},"fn_name":null},{"line":656,"address":[867967,867936],"length":1,"stats":{"Line":0},"fn_name":"get_categoria_c"},{"line":657,"address":[867949],"length":1,"stats":{"Line":0},"fn_name":null},{"line":658,"address":[868020,867958],"length":1,"stats":{"Line":0},"fn_name":null},{"line":659,"address":[867991],"length":1,"stats":{"Line":0},"fn_name":null},{"line":671,"address":[872080],"length":1,"stats":{"Line":0},"fn_name":"existe_socio"},{"line":672,"address":[872114],"length":1,"stats":{"Line":0},"fn_name":null},{"line":673,"address":[872119],"length":1,"stats":{"Line":0},"fn_name":null},{"line":674,"address":[872307,872133],"length":1,"stats":{"Line":0},"fn_name":null},{"line":675,"address":[872296,872211],"length":1,"stats":{"Line":0},"fn_name":null},{"line":676,"address":[872291],"length":1,"stats":{"Line":0},"fn_name":null},{"line":678,"address":[872312,872302,872269],"length":1,"stats":{"Line":0},"fn_name":null},{"line":693,"address":[868032,868134],"length":1,"stats":{"Line":0},"fn_name":"get_socios"},{"line":694,"address":[868059],"length":1,"stats":{"Line":0},"fn_name":null},{"line":695,"address":[868073,868123],"length":1,"stats":{"Line":0},"fn_name":null},{"line":696,"address":[868144],"length":1,"stats":{"Line":0},"fn_name":null},{"line":697,"address":[868261],"length":1,"stats":{"Line":0},"fn_name":null},{"line":715,"address":[868304,868444],"length":1,"stats":{"Line":0},"fn_name":"get_pago"},{"line":716,"address":[868363],"length":1,"stats":{"Line":0},"fn_name":null},{"line":717,"address":[868433,868377],"length":1,"stats":{"Line":0},"fn_name":null},{"line":718,"address":[868467],"length":1,"stats":{"Line":0},"fn_name":null},{"line":719,"address":[868535],"length":1,"stats":{"Line":0},"fn_name":null},{"line":720,"address":[868668],"length":1,"stats":{"Line":0},"fn_name":null},{"line":721,"address":[868698],"length":1,"stats":{"Line":0},"fn_name":null},{"line":722,"address":[868761],"length":1,"stats":{"Line":0},"fn_name":null},{"line":727,"address":[868488,868830],"length":1,"stats":{"Line":0},"fn_name":null},{"line":742,"address":[869730,868896],"length":1,"stats":{"Line":0},"fn_name":"get_info_socio"},{"line":743,"address":[868960],"length":1,"stats":{"Line":0},"fn_name":null},{"line":745,"address":[869123,869047],"length":1,"stats":{"Line":0},"fn_name":null},{"line":746,"address":[869325,869186],"length":1,"stats":{"Line":0},"fn_name":null},{"line":747,"address":[869385,869251],"length":1,"stats":{"Line":0},"fn_name":null},{"line":748,"address":[869383,869275],"length":1,"stats":{"Line":0},"fn_name":null},{"line":749,"address":[869299],"length":1,"stats":{"Line":0},"fn_name":null},{"line":750,"address":[869249],"length":1,"stats":{"Line":0},"fn_name":null},{"line":752,"address":[869356],"length":1,"stats":{"Line":0},"fn_name":null},{"line":753,"address":[870126,869473,869397],"length":1,"stats":{"Line":0},"fn_name":null},{"line":754,"address":[869519,869970,870003],"length":1,"stats":{"Line":0},"fn_name":null},{"line":755,"address":[869740,870001],"length":1,"stats":{"Line":0},"fn_name":null},{"line":757,"address":[869999,869770],"length":1,"stats":{"Line":0},"fn_name":null},{"line":759,"address":[869800,869997],"length":1,"stats":{"Line":0},"fn_name":null},{"line":761,"address":[869830,869995],"length":1,"stats":{"Line":0},"fn_name":null},{"line":763,"address":[869993,869860],"length":1,"stats":{"Line":0},"fn_name":null},{"line":765,"address":[869887,869991],"length":1,"stats":{"Line":0},"fn_name":null},{"line":767,"address":[869914,869989],"length":1,"stats":{"Line":0},"fn_name":null},{"line":769,"address":[869941],"length":1,"stats":{"Line":0},"fn_name":null},{"line":771,"address":[869738],"length":1,"stats":{"Line":0},"fn_name":null},{"line":775,"address":[869556],"length":1,"stats":{"Line":0},"fn_name":null},{"line":776,"address":[869424,870142,869134],"length":1,"stats":{"Line":0},"fn_name":null},{"line":778,"address":[868977],"length":1,"stats":{"Line":0},"fn_name":null},{"line":793,"address":[882976,883863,883919],"length":1,"stats":{"Line":0},"fn_name":"crear_socio"},{"line":794,"address":[883210,883111],"length":1,"stats":{"Line":0},"fn_name":null},{"line":795,"address":[883292,883226],"length":1,"stats":{"Line":0},"fn_name":null},{"line":796,"address":[883350,883389,883269],"length":1,"stats":{"Line":0},"fn_name":null},{"line":797,"address":[883451,883366,883403],"length":1,"stats":{"Line":0},"fn_name":null},{"line":798,"address":[883835,883409],"length":1,"stats":{"Line":0},"fn_name":null},{"line":800,"address":[883300,883464],"length":1,"stats":{"Line":0},"fn_name":null},{"line":801,"address":[883466],"length":1,"stats":{"Line":0},"fn_name":null},{"line":802,"address":[883481,883742],"length":1,"stats":{"Line":0},"fn_name":null},{"line":803,"address":[883534],"length":1,"stats":{"Line":0},"fn_name":null},{"line":822,"address":[884463,883936],"length":1,"stats":{"Line":0},"fn_name":"elegir_actividad"},{"line":823,"address":[884013,883948],"length":1,"stats":{"Line":0},"fn_name":null},{"line":824,"address":[884095,884029],"length":1,"stats":{"Line":0},"fn_name":null},{"line":825,"address":[884166,884127,884072],"length":1,"stats":{"Line":0},"fn_name":null},{"line":826,"address":[884216,884143,884177],"length":1,"stats":{"Line":0},"fn_name":null},{"line":827,"address":[884227,884266,884193],"length":1,"stats":{"Line":0},"fn_name":null},{"line":828,"address":[884280,884243,884319],"length":1,"stats":{"Line":0},"fn_name":null},{"line":829,"address":[884296,884333,884372],"length":1,"stats":{"Line":0},"fn_name":null},{"line":830,"address":[884349,884386,884428],"length":1,"stats":{"Line":0},"fn_name":null},{"line":831,"address":[884438,884392],"length":1,"stats":{"Line":0},"fn_name":null},{"line":846,"address":[884496],"length":1,"stats":{"Line":0},"fn_name":"crear_pago"},{"line":870,"address":[884704],"length":1,"stats":{"Line":0},"fn_name":"esta_vencido"},{"line":871,"address":[884717],"length":1,"stats":{"Line":0},"fn_name":null},{"line":872,"address":[884722],"length":1,"stats":{"Line":0},"fn_name":null},{"line":873,"address":[884742,884767],"length":1,"stats":{"Line":0},"fn_name":null},{"line":874,"address":[884762],"length":1,"stats":{"Line":0},"fn_name":null}],"/home/usuario/Escritorio/reporte/club/src/coverage/debug/build/anyhow-586e70f671500c55/out/probe.rs":[{"line":21,"address":[],"length":0,"stats":{"Line":0},"fn_name":null},{"line":22,"address":[],"length":0,"stats":{"Line":0},"fn_name":null}],"/home/usuario/Escritorio/reporte/club/src/coverage/debug/build/anyhow-b80f95abb5dfdb91/out/probe.rs":[{"line":21,"address":[],"length":0,"stats":{"Line":0},"fn_name":null},{"line":22,"address":[],"length":0,"stats":{"Line":0},"fn_name":null}],"/home/usuario/Escritorio/reporte/club/src/coverage/debug/build/crunchy-727ae2a0f5221af9/out/lib.rs":[],"/home/usuario/Escritorio/reporte/club/src/coverage/debug/build/crunchy-8eba14b09fd668f6/out/lib.rs":[],"/home/usuario/Escritorio/reporte/club/src/coverage/debug/build/crunchy-978d90d926adf544/out/lib.rs":[],"/home/usuario/Escritorio/reporte/club/src/coverage/debug/build/crunchy-d94aa0f95104665b/out/lib.rs":[],"/home/usuario/Escritorio/reporte/club/src/coverage/debug/build/libsecp256k1-487bcb62dc549a43/out/const.rs":[],"/home/usuario/Escritorio/reporte/club/src/coverage/debug/build/libsecp256k1-487bcb62dc549a43/out/const_gen.rs":[],"/home/usuario/Escritorio/reporte/club/src/coverage/debug/build/libsecp256k1-b182def13a4f4651/out/const.rs":[],"/home/usuario/Escritorio/reporte/club/src/coverage/debug/build/libsecp256k1-b182def13a4f4651/out/const_gen.rs":[],"/home/usuario/Escritorio/reporte/club/src/coverage/debug/build/num-bigint-5cd32e7e527b75b7/out/radix_bases.rs":[],"/home/usuario/Escritorio/reporte/club/src/coverage/debug/build/num-bigint-9552ecd37c05bccb/out/radix_bases.rs":[],"/home/usuario/Escritorio/reporte/club/src/coverage/debug/build/ss58-registry-19a577034f39c6c7/out/registry_gen.rs":[],"/home/usuario/Escritorio/reporte/club/src/coverage/debug/build/ss58-registry-9bb354c2fd9374b1/out/registry_gen.rs":[],"/home/usuario/Escritorio/reporte/club/src/coverage/debug/build/target-lexicon-1aca5818b989e5ff/out/host.rs":[],"/home/usuario/Escritorio/reporte/club/src/coverage/debug/build/target-lexicon-b046d8b29187587d/out/host.rs":[],"/home/usuario/Escritorio/reporte/club/src/coverage/debug/build/thiserror-256c516b586d8186/out/probe.rs":[{"line":6,"address":[],"length":0,"stats":{"Line":0},"fn_name":null},{"line":7,"address":[],"length":0,"stats":{"Line":0},"fn_name":null}],"/home/usuario/Escritorio/reporte/club/src/coverage/debug/build/thiserror-4792f91c8f3a98b4/out/probe.rs":[{"line":6,"address":[],"length":0,"stats":{"Line":0},"fn_name":null},{"line":7,"address":[],"length":0,"stats":{"Line":0},"fn_name":null}],"/home/usuario/Escritorio/reporte/club/src/coverage/debug/build/typenum-a1308da57b6c3636/out/consts.rs":[],"/home/usuario/Escritorio/reporte/club/src/coverage/debug/build/typenum-a1308da57b6c3636/out/op.rs":[],"/home/usuario/Escritorio/reporte/club/src/coverage/debug/build/typenum-a1308da57b6c3636/out/tests.rs":[],"/home/usuario/Escritorio/reporte/club/src/coverage/debug/build/typenum-e33d14a6ec63fd2b/out/consts.rs":[],"/home/usuario/Escritorio/reporte/club/src/coverage/debug/build/typenum-e33d14a6ec63fd2b/out/op.rs":[],"/home/usuario/Escritorio/reporte/club/src/coverage/debug/build/typenum-e33d14a6ec63fd2b/out/tests.rs":[],"/home/usuario/Escritorio/reporte/club/src/coverage/debug/build/wasm-opt-cxx-sys-365c26f85ff2c6b0/out/cxxbridge/include/wasm-opt-cxx-sys/src/lib.rs":[],"/home/usuario/Escritorio/reporte/club/src/coverage/debug/build/wasm-opt-sys-8a3a8de0ba6191de/out/cxxbridge/include/wasm-opt-sys/src/lib.rs":[],"/home/usuario/Escritorio/reporte/club/target/debug/build/anyhow-586e70f671500c55/out/probe.rs":[{"line":21,"address":[],"length":0,"stats":{"Line":0},"fn_name":null},{"line":22,"address":[],"length":0,"stats":{"Line":0},"fn_name":null}],"/home/usuario/Escritorio/reporte/club/target/debug/build/anyhow-b80f95abb5dfdb91/out/probe.rs":[{"line":21,"address":[],"length":0,"stats":{"Line":0},"fn_name":null},{"line":22,"address":[],"length":0,"stats":{"Line":0},"fn_name":null}],"/home/usuario/Escritorio/reporte/club/target/debug/build/crunchy-727ae2a0f5221af9/out/lib.rs":[],"/home/usuario/Escritorio/reporte/club/target/debug/build/crunchy-8eba14b09fd668f6/out/lib.rs":[],"/home/usuario/Escritorio/reporte/club/target/debug/build/crunchy-978d90d926adf544/out/lib.rs":[],"/home/usuario/Escritorio/reporte/club/target/debug/build/crunchy-d94aa0f95104665b/out/lib.rs":[],"/home/usuario/Escritorio/reporte/club/target/debug/build/libsecp256k1-487bcb62dc549a43/out/const.rs":[],"/home/usuario/Escritorio/reporte/club/target/debug/build/libsecp256k1-487bcb62dc549a43/out/const_gen.rs":[],"/home/usuario/Escritorio/reporte/club/target/debug/build/libsecp256k1-b182def13a4f4651/out/const.rs":[],"/home/usuario/Escritorio/reporte/club/target/debug/build/libsecp256k1-b182def13a4f4651/out/const_gen.rs":[],"/home/usuario/Escritorio/reporte/club/target/debug/build/libsecp256k1-d156a9507e1f5ddc/out/const.rs":[],"/home/usuario/Escritorio/reporte/club/target/debug/build/libsecp256k1-d156a9507e1f5ddc/out/const_gen.rs":[],"/home/usuario/Escritorio/reporte/club/target/debug/build/num-bigint-5cd32e7e527b75b7/out/radix_bases.rs":[],"/home/usuario/Escritorio/reporte/club/target/debug/build/num-bigint-9552ecd37c05bccb/out/radix_bases.rs":[],"/home/usuario/Escritorio/reporte/club/target/debug/build/ss58-registry-19a577034f39c6c7/out/registry_gen.rs":[],"/home/usuario/Escritorio/reporte/club/target/debug/build/ss58-registry-9bb354c2fd9374b1/out/registry_gen.rs":[],"/home/usuario/Escritorio/reporte/club/target/debug/build/ss58-registry-cde7ebc7adbf06fa/out/registry_gen.rs":[],"/home/usuario/Escritorio/reporte/club/target/debug/build/target-lexicon-1aca5818b989e5ff/out/host.rs":[],"/home/usuario/Escritorio/reporte/club/target/debug/build/target-lexicon-b046d8b29187587d/out/host.rs":[],"/home/usuario/Escritorio/reporte/club/target/debug/build/thiserror-256c516b586d8186/out/probe.rs":[{"line":6,"address":[],"length":0,"stats":{"Line":0},"fn_name":null},{"line":7,"address":[],"length":0,"stats":{"Line":0},"fn_name":null}],"/home/usuario/Escritorio/reporte/club/target/debug/build/thiserror-4792f91c8f3a98b4/out/probe.rs":[{"line":6,"address":[],"length":0,"stats":{"Line":0},"fn_name":null},{"line":7,"address":[],"length":0,"stats":{"Line":0},"fn_name":null}],"/home/usuario/Escritorio/reporte/club/target/debug/build/typenum-a1308da57b6c3636/out/consts.rs":[],"/home/usuario/Escritorio/reporte/club/target/debug/build/typenum-a1308da57b6c3636/out/op.rs":[],"/home/usuario/Escritorio/reporte/club/target/debug/build/typenum-a1308da57b6c3636/out/tests.rs":[],"/home/usuario/Escritorio/reporte/club/target/debug/build/typenum-e33d14a6ec63fd2b/out/consts.rs":[],"/home/usuario/Escritorio/reporte/club/target/debug/build/typenum-e33d14a6ec63fd2b/out/op.rs":[],"/home/usuario/Escritorio/reporte/club/target/debug/build/typenum-e33d14a6ec63fd2b/out/tests.rs":[],"/home/usuario/Escritorio/reporte/club/target/debug/build/wasm-opt-cxx-sys-365c26f85ff2c6b0/out/cxxbridge/include/wasm-opt-cxx-sys/src/lib.rs":[],"/home/usuario/Escritorio/reporte/club/target/debug/build/wasm-opt-sys-8a3a8de0ba6191de/out/cxxbridge/include/wasm-opt-sys/src/lib.rs":[],"/home/usuario/Escritorio/reporte/club/target/ink/release/build/thiserror-3cdfd6d830daa6e9/out/probe.rs":[{"line":6,"address":[],"length":0,"stats":{"Line":0},"fn_name":null},{"line":7,"address":[],"length":0,"stats":{"Line":0},"fn_name":null}],"/home/usuario/Escritorio/reporte/club/target/ink/release/build/thiserror-42040cdd22cc6deb/out/probe.rs":[{"line":6,"address":[],"length":0,"stats":{"Line":0},"fn_name":null},{"line":7,"address":[],"length":0,"stats":{"Line":0},"fn_name":null}],"/home/usuario/Escritorio/reporte/club/target/ink/release/build/thiserror-833b541841470540/out/probe.rs":[{"line":6,"address":[],"length":0,"stats":{"Line":0},"fn_name":null},{"line":7,"address":[],"length":0,"stats":{"Line":0},"fn_name":null}],"/home/usuario/Escritorio/reporte/club/target/ink/release/build/thiserror-854560927b904642/out/probe.rs":[{"line":6,"address":[],"length":0,"stats":{"Line":0},"fn_name":null},{"line":7,"address":[],"length":0,"stats":{"Line":0},"fn_name":null}],"/home/usuario/Escritorio/reporte/club/target/ink/release/build/thiserror-8602f9046a7cca9e/out/probe.rs":[{"line":6,"address":[],"length":0,"stats":{"Line":0},"fn_name":null},{"line":7,"address":[],"length":0,"stats":{"Line":0},"fn_name":null}],"/home/usuario/Escritorio/reporte/club/target/ink/release/build/thiserror-951a9d235b646385/out/probe.rs":[{"line":6,"address":[],"length":0,"stats":{"Line":0},"fn_name":null},{"line":7,"address":[],"length":0,"stats":{"Line":0},"fn_name":null}],"/home/usuario/Escritorio/reporte/club/target/ink/release/build/thiserror-ae2ae0b835c49ce2/out/probe.rs":[{"line":6,"address":[],"length":0,"stats":{"Line":0},"fn_name":null},{"line":7,"address":[],"length":0,"stats":{"Line":0},"fn_name":null}],"/home/usuario/Escritorio/reporte/club/target/ink/release/build/typenum-045e96f682004cfc/out/consts.rs":[],"/home/usuario/Escritorio/reporte/club/target/ink/release/build/typenum-045e96f682004cfc/out/op.rs":[],"/home/usuario/Escritorio/reporte/club/target/ink/release/build/typenum-045e96f682004cfc/out/tests.rs":[],"/home/usuario/Escritorio/reporte/club/target/ink/release/build/typenum-29d4d56851fe265b/out/consts.rs":[],"/home/usuario/Escritorio/reporte/club/target/ink/release/build/typenum-29d4d56851fe265b/out/op.rs":[],"/home/usuario/Escritorio/reporte/club/target/ink/release/build/typenum-29d4d56851fe265b/out/tests.rs":[],"/home/usuario/Escritorio/reporte/club/target/ink/release/build/typenum-5aa23655da4ec47a/out/consts.rs":[],"/home/usuario/Escritorio/reporte/club/target/ink/release/build/typenum-5aa23655da4ec47a/out/op.rs":[],"/home/usuario/Escritorio/reporte/club/target/ink/release/build/typenum-5aa23655da4ec47a/out/tests.rs":[],"/home/usuario/Escritorio/reporte/club/target/ink/release/build/typenum-883c02f1c5d5db57/out/consts.rs":[],"/home/usuario/Escritorio/reporte/club/target/ink/release/build/typenum-883c02f1c5d5db57/out/op.rs":[],"/home/usuario/Escritorio/reporte/club/target/ink/release/build/typenum-883c02f1c5d5db57/out/tests.rs":[],"/home/usuario/Escritorio/reporte/club/target/ink/release/build/typenum-c4175b10cf969f5a/out/consts.rs":[],"/home/usuario/Escritorio/reporte/club/target/ink/release/build/typenum-c4175b10cf969f5a/out/op.rs":[],"/home/usuario/Escritorio/reporte/club/target/ink/release/build/typenum-c4175b10cf969f5a/out/tests.rs":[],"/home/usuario/Escritorio/reporte/club/target/ink/release/build/typenum-e4960ad4f4c0f0d7/out/consts.rs":[],"/home/usuario/Escritorio/reporte/club/target/ink/release/build/typenum-e4960ad4f4c0f0d7/out/op.rs":[],"/home/usuario/Escritorio/reporte/club/target/ink/release/build/typenum-e4960ad4f4c0f0d7/out/tests.rs":[],"/home/usuario/Escritorio/reporte/club/target/ink/release/build/typenum-fb6645ee6d48d1ef/out/consts.rs":[],"/home/usuario/Escritorio/reporte/club/target/ink/release/build/typenum-fb6645ee6d48d1ef/out/op.rs":[],"/home/usuario/Escritorio/reporte/club/target/ink/release/build/typenum-fb6645ee6d48d1ef/out/tests.rs":[],"/home/usuario/Escritorio/reporte/lib.rs":[{"line":4,"address":[491782,478081,492282,493448,494231,492413,497038,491454,496311,490265,491099,478080,496610,497381,491392,494117,495447,492690,496396,492913,490918,493095,478064,496824,497527,491056,490880,491222,495173,497167,493027,478069,491760,492007,494604,492547,496144,496739,497252,494299,496525,496953,493600,495021],"length":1,"stats":{"Line":0},"fn_name":"env"},{"line":57,"address":[497744],"length":1,"stats":{"Line":4},"fn_name":"crear_socio"},{"line":71,"address":[497824],"length":1,"stats":{"Line":5},"fn_name":"crear_pago"},{"line":94,"address":[484304],"length":1,"stats":{"Line":6},"fn_name":"new"},{"line":120,"address":[484320],"length":1,"stats":{"Line":5},"fn_name":"tiempo"},{"line":130,"address":[487327,484888,484352],"length":1,"stats":{"Line":1},"fn_name":"crear_info"},{"line":131,"address":[484391],"length":1,"stats":{"Line":1},"fn_name":null},{"line":132,"address":[484476],"length":1,"stats":{"Line":4},"fn_name":null},{"line":137,"address":[484651,484718],"length":1,"stats":{"Line":8},"fn_name":null},{"line":138,"address":[484899],"length":1,"stats":{"Line":5},"fn_name":null},{"line":139,"address":[485099],"length":1,"stats":{"Line":5},"fn_name":null},{"line":140,"address":[485299],"length":1,"stats":{"Line":5},"fn_name":null},{"line":141,"address":[485499],"length":1,"stats":{"Line":5},"fn_name":null},{"line":142,"address":[485699],"length":1,"stats":{"Line":5},"fn_name":null},{"line":144,"address":[485907],"length":1,"stats":{"Line":5},"fn_name":null},{"line":145,"address":[486020],"length":1,"stats":{"Line":5},"fn_name":null},{"line":146,"address":[486152],"length":1,"stats":{"Line":5},"fn_name":null},{"line":147,"address":[486284],"length":1,"stats":{"Line":5},"fn_name":null},{"line":148,"address":[486416],"length":1,"stats":{"Line":5},"fn_name":null},{"line":149,"address":[486536],"length":1,"stats":{"Line":5},"fn_name":null},{"line":150,"address":[486648],"length":1,"stats":{"Line":4},"fn_name":null},{"line":151,"address":[486757],"length":1,"stats":{"Line":5},"fn_name":null},{"line":152,"address":[486877],"length":1,"stats":{"Line":5},"fn_name":null},{"line":153,"address":[486989],"length":1,"stats":{"Line":5},"fn_name":null},{"line":154,"address":[487098],"length":1,"stats":{"Line":5},"fn_name":null},{"line":155,"address":[487210],"length":1,"stats":{"Line":5},"fn_name":null},{"line":160,"address":[487932,487863,487360],"length":1,"stats":{"Line":1},"fn_name":"get_socios"},{"line":161,"address":[487384],"length":1,"stats":{"Line":1},"fn_name":null},{"line":162,"address":[487415],"length":1,"stats":{"Line":1},"fn_name":null},{"line":163,"address":[487467,487550],"length":1,"stats":{"Line":2},"fn_name":null},{"line":164,"address":[487778],"length":1,"stats":{"Line":1},"fn_name":null},{"line":171,"address":[488189,487952],"length":1,"stats":{"Line":1},"fn_name":"get_pagos"},{"line":172,"address":[487992],"length":1,"stats":{"Line":1},"fn_name":null},{"line":173,"address":[488106,487997,488066],"length":1,"stats":{"Line":5},"fn_name":null},{"line":175,"address":[488098],"length":1,"stats":{"Line":6},"fn_name":null},{"line":176,"address":[506416,506400],"length":1,"stats":{"Line":4},"fn_name":"{closure#1}"},{"line":182,"address":[488553,488224],"length":1,"stats":{"Line":1},"fn_name":"get_info_socio"},{"line":183,"address":[488280],"length":1,"stats":{"Line":1},"fn_name":null},{"line":184,"address":[488295,488356],"length":1,"stats":{"Line":2},"fn_name":null},{"line":191,"address":[480576,481138],"length":1,"stats":{"Line":2},"fn_name":"get_pagos_pendientes"},{"line":192,"address":[480609],"length":1,"stats":{"Line":1},"fn_name":null},{"line":193,"address":[480689,480636],"length":1,"stats":{"Line":2},"fn_name":null},{"line":194,"address":[480752,480697],"length":1,"stats":{"Line":2},"fn_name":null},{"line":195,"address":[480760],"length":1,"stats":{"Line":1},"fn_name":null},{"line":196,"address":[481059],"length":1,"stats":{"Line":1},"fn_name":null},{"line":197,"address":[481098],"length":1,"stats":{"Line":1},"fn_name":null},{"line":207,"address":[488592,488965],"length":1,"stats":{"Line":1},"fn_name":"es_moroso"},{"line":208,"address":[488644],"length":1,"stats":{"Line":1},"fn_name":null},{"line":209,"address":[488649],"length":1,"stats":{"Line":1},"fn_name":null},{"line":210,"address":[488654],"length":1,"stats":{"Line":2},"fn_name":null},{"line":211,"address":[488928,488663,488741],"length":1,"stats":{"Line":6},"fn_name":null},{"line":212,"address":[488800],"length":1,"stats":{"Line":2},"fn_name":null},{"line":213,"address":[488916,488866],"length":1,"stats":{"Line":4},"fn_name":null},{"line":214,"address":[488911],"length":1,"stats":{"Line":2},"fn_name":null},{"line":217,"address":[488923,488933,488843],"length":1,"stats":{"Line":4},"fn_name":null},{"line":232,"address":[481184,481365,491178],"length":1,"stats":{"Line":2},"fn_name":"get_socios_no_morosos_actividad_especifica"},{"line":233,"address":[481225],"length":1,"stats":{"Line":1},"fn_name":null},{"line":234,"address":[481287,481340],"length":1,"stats":{"Line":2},"fn_name":null},{"line":235,"address":[481386],"length":1,"stats":{"Line":1},"fn_name":null},{"line":236,"address":[481398,481459],"length":1,"stats":{"Line":2},"fn_name":null},{"line":237,"address":[481672,481467],"length":1,"stats":{"Line":2},"fn_name":null},{"line":238,"address":[481705],"length":1,"stats":{"Line":1},"fn_name":null},{"line":239,"address":[481803,481717],"length":1,"stats":{"Line":2},"fn_name":null},{"line":240,"address":[481853],"length":1,"stats":{"Line":1},"fn_name":null},{"line":241,"address":[481920],"length":1,"stats":{"Line":1},"fn_name":null},{"line":243,"address":[481889,481984],"length":1,"stats":{"Line":2},"fn_name":null},{"line":244,"address":[481998],"length":1,"stats":{"Line":1},"fn_name":null},{"line":245,"address":[482035],"length":1,"stats":{"Line":1},"fn_name":null},{"line":255,"address":[488992],"length":1,"stats":{"Line":1},"fn_name":"es_actividad_valida"},{"line":256,"address":[489019],"length":1,"stats":{"Line":1},"fn_name":null},{"line":257,"address":[489040,489094],"length":1,"stats":{"Line":2},"fn_name":null},{"line":258,"address":[489071,489146],"length":1,"stats":{"Line":2},"fn_name":null},{"line":259,"address":[489186,489123],"length":1,"stats":{"Line":2},"fn_name":null},{"line":260,"address":[489163,489226],"length":1,"stats":{"Line":2},"fn_name":null},{"line":261,"address":[489203,489269],"length":1,"stats":{"Line":2},"fn_name":null},{"line":262,"address":[489246,489312],"length":1,"stats":{"Line":2},"fn_name":null},{"line":263,"address":[489382,489289],"length":1,"stats":{"Line":2},"fn_name":null},{"line":264,"address":[489322],"length":1,"stats":{"Line":1},"fn_name":null},{"line":271,"address":[489392],"length":1,"stats":{"Line":1},"fn_name":"calcular_fecha"},{"line":272,"address":[489432],"length":1,"stats":{"Line":1},"fn_name":null},{"line":273,"address":[489441],"length":1,"stats":{"Line":1},"fn_name":null},{"line":274,"address":[489450],"length":1,"stats":{"Line":1},"fn_name":null},{"line":281,"address":[489487],"length":1,"stats":{"Line":1},"fn_name":null},{"line":282,"address":[489502],"length":1,"stats":{"Line":1},"fn_name":null},{"line":284,"address":[489525],"length":1,"stats":{"Line":1},"fn_name":null},{"line":285,"address":[489540,489563],"length":1,"stats":{"Line":2},"fn_name":null},{"line":286,"address":[489573],"length":1,"stats":{"Line":1},"fn_name":null},{"line":294,"address":[484263,482128],"length":1,"stats":{"Line":2},"fn_name":"recaudacion_mensual"},{"line":295,"address":[482202],"length":1,"stats":{"Line":1},"fn_name":null},{"line":296,"address":[482231],"length":1,"stats":{"Line":1},"fn_name":null},{"line":297,"address":[482255],"length":1,"stats":{"Line":1},"fn_name":null},{"line":298,"address":[482279],"length":1,"stats":{"Line":1},"fn_name":null},{"line":299,"address":[482311],"length":1,"stats":{"Line":1},"fn_name":null},{"line":300,"address":[482638,482359,482435],"length":1,"stats":{"Line":3},"fn_name":null},{"line":301,"address":[482662],"length":1,"stats":{"Line":1},"fn_name":null},{"line":302,"address":[482758],"length":1,"stats":{"Line":1},"fn_name":null},{"line":303,"address":[483076,482817,482881],"length":1,"stats":{"Line":3},"fn_name":null},{"line":304,"address":[483100],"length":1,"stats":{"Line":1},"fn_name":null},{"line":305,"address":[483173],"length":1,"stats":{"Line":1},"fn_name":null},{"line":306,"address":[483243],"length":1,"stats":{"Line":1},"fn_name":null},{"line":307,"address":[483292,483369],"length":1,"stats":{"Line":2},"fn_name":null},{"line":308,"address":[483335,483515,483565],"length":1,"stats":{"Line":3},"fn_name":null},{"line":309,"address":[483531,483712],"length":1,"stats":{"Line":2},"fn_name":null},{"line":315,"address":[482608,483913],"length":1,"stats":{"Line":2},"fn_name":null},{"line":316,"address":[483992],"length":1,"stats":{"Line":1},"fn_name":null},{"line":317,"address":[484106],"length":1,"stats":{"Line":1},"fn_name":null},{"line":318,"address":[484220],"length":1,"stats":{"Line":1},"fn_name":null},{"line":324,"address":[497936],"length":1,"stats":{"Line":1},"fn_name":"es_bisiesto"},{"line":325,"address":[497949],"length":1,"stats":{"Line":1},"fn_name":null},{"line":326,"address":[497954],"length":1,"stats":{"Line":1},"fn_name":null},{"line":327,"address":[497972,498067,498017],"length":1,"stats":{"Line":2},"fn_name":null},{"line":328,"address":[498062],"length":1,"stats":{"Line":0},"fn_name":null},{"line":332,"address":[497994],"length":1,"stats":{"Line":1},"fn_name":null},{"line":337,"address":[498080],"length":1,"stats":{"Line":1},"fn_name":"sumar_dias"},{"line":338,"address":[498099],"length":1,"stats":{"Line":1},"fn_name":null},{"line":340,"address":[498117],"length":1,"stats":{"Line":1},"fn_name":null},{"line":341,"address":[498287],"length":1,"stats":{"Line":1},"fn_name":null},{"line":342,"address":[498298],"length":1,"stats":{"Line":1},"fn_name":null},{"line":343,"address":[498314,498352],"length":1,"stats":{"Line":2},"fn_name":null},{"line":344,"address":[498276],"length":1,"stats":{"Line":0},"fn_name":null},{"line":346,"address":[498582,498379,498330],"length":1,"stats":{"Line":3},"fn_name":null},{"line":347,"address":[498476,498542],"length":1,"stats":{"Line":1},"fn_name":null},{"line":348,"address":[498509,498587,498577],"length":1,"stats":{"Line":2},"fn_name":null},{"line":350,"address":[498627,498724,498423],"length":1,"stats":{"Line":2},"fn_name":null},{"line":351,"address":[498695],"length":1,"stats":{"Line":1},"fn_name":null},{"line":352,"address":[498780,498702,498764],"length":1,"stats":{"Line":2},"fn_name":null},{"line":353,"address":[498768,498855],"length":1,"stats":{"Line":2},"fn_name":null},{"line":354,"address":[498815,498860],"length":1,"stats":{"Line":1},"fn_name":null},{"line":355,"address":[498847],"length":1,"stats":{"Line":1},"fn_name":null}],"/home/usuario/Escritorio/reporte/target/ink/release/build/thiserror-3cdfd6d830daa6e9/out/probe.rs":[{"line":6,"address":[],"length":0,"stats":{"Line":0},"fn_name":null},{"line":7,"address":[],"length":0,"stats":{"Line":0},"fn_name":null}],"/home/usuario/Escritorio/reporte/target/ink/release/build/thiserror-42040cdd22cc6deb/out/probe.rs":[{"line":6,"address":[],"length":0,"stats":{"Line":0},"fn_name":null},{"line":7,"address":[],"length":0,"stats":{"Line":0},"fn_name":null}],"/home/usuario/Escritorio/reporte/target/ink/release/build/thiserror-854560927b904642/out/probe.rs":[{"line":6,"address":[],"length":0,"stats":{"Line":0},"fn_name":null},{"line":7,"address":[],"length":0,"stats":{"Line":0},"fn_name":null}],"/home/usuario/Escritorio/reporte/target/ink/release/build/thiserror-8602f9046a7cca9e/out/probe.rs":[{"line":6,"address":[],"length":0,"stats":{"Line":0},"fn_name":null},{"line":7,"address":[],"length":0,"stats":{"Line":0},"fn_name":null}],"/home/usuario/Escritorio/reporte/target/ink/release/build/thiserror-8edefd1c128a3d4a/out/probe.rs":[{"line":6,"address":[],"length":0,"stats":{"Line":0},"fn_name":null},{"line":7,"address":[],"length":0,"stats":{"Line":0},"fn_name":null}],"/home/usuario/Escritorio/reporte/target/ink/release/build/thiserror-ae2ae0b835c49ce2/out/probe.rs":[{"line":6,"address":[],"length":0,"stats":{"Line":0},"fn_name":null},{"line":7,"address":[],"length":0,"stats":{"Line":0},"fn_name":null}],"/home/usuario/Escritorio/reporte/target/ink/release/build/thiserror-f711d4897c92e981/out/probe.rs":[{"line":6,"address":[],"length":0,"stats":{"Line":0},"fn_name":null},{"line":7,"address":[],"length":0,"stats":{"Line":0},"fn_name":null}],"/home/usuario/Escritorio/reporte/target/ink/release/build/typenum-045e96f682004cfc/out/consts.rs":[],"/home/usuario/Escritorio/reporte/target/ink/release/build/typenum-045e96f682004cfc/out/op.rs":[],"/home/usuario/Escritorio/reporte/target/ink/release/build/typenum-045e96f682004cfc/out/tests.rs":[],"/home/usuario/Escritorio/reporte/target/ink/release/build/typenum-1bb1d0f4b669a48d/out/consts.rs":[],"/home/usuario/Escritorio/reporte/target/ink/release/build/typenum-1bb1d0f4b669a48d/out/op.rs":[],"/home/usuario/Escritorio/reporte/target/ink/release/build/typenum-1bb1d0f4b669a48d/out/tests.rs":[],"/home/usuario/Escritorio/reporte/target/ink/release/build/typenum-29d4d56851fe265b/out/consts.rs":[],"/home/usuario/Escritorio/reporte/target/ink/release/build/typenum-29d4d56851fe265b/out/op.rs":[],"/home/usuario/Escritorio/reporte/target/ink/release/build/typenum-29d4d56851fe265b/out/tests.rs":[],"/home/usuario/Escritorio/reporte/target/ink/release/build/typenum-5aa23655da4ec47a/out/consts.rs":[],"/home/usuario/Escritorio/reporte/target/ink/release/build/typenum-5aa23655da4ec47a/out/op.rs":[],"/home/usuario/Escritorio/reporte/target/ink/release/build/typenum-5aa23655da4ec47a/out/tests.rs":[],"/home/usuario/Escritorio/reporte/target/ink/release/build/typenum-b61eca48a2837c3f/out/consts.rs":[],"/home/usuario/Escritorio/reporte/target/ink/release/build/typenum-b61eca48a2837c3f/out/op.rs":[],"/home/usuario/Escritorio/reporte/target/ink/release/build/typenum-b61eca48a2837c3f/out/tests.rs":[],"/home/usuario/Escritorio/reporte/target/ink/release/build/typenum-c4175b10cf969f5a/out/consts.rs":[],"/home/usuario/Escritorio/reporte/target/ink/release/build/typenum-c4175b10cf969f5a/out/op.rs":[],"/home/usuario/Escritorio/reporte/target/ink/release/build/typenum-c4175b10cf969f5a/out/tests.rs":[],"/home/usuario/Escritorio/reporte/target/ink/release/build/typenum-e4960ad4f4c0f0d7/out/consts.rs":[],"/home/usuario/Escritorio/reporte/target/ink/release/build/typenum-e4960ad4f4c0f0d7/out/op.rs":[],"/home/usuario/Escritorio/reporte/target/ink/release/build/typenum-e4960ad4f4c0f0d7/out/tests.rs":[]}}